core/__init__.py
core/config.py
core/io_utils.py
core/messages.py
core/rabbit.py
core/sessions.py
core/providers/__init__.py
rabbit_ai_cli-0.0.12.dist-info/licenses/LICENSE
rabbit_ai_cli-0.0.12.dist-info/METADATA
rabbit_ai_cli-0.0.12.dist-info/WHEEL
rabbit_ai_cli-0.0.12.dist-info/entry_points.txt
rabbit_ai_cli-0.0.12.dist-info/top_level.txt
rabbit_ai_cli-0.0.12.dist-info/RECORD
