Metadata-Version: 2.4
Name: rabbit-ai-cli
Version: 0.0.12
Summary: A tiny, extensible AI CLI for terminal workflows
Author-email: zeecaniago <zeecaniago@gmail.com>
License: MIT
Project-URL: Homepage, https://github.com/zeecaniago/rabbit
Project-URL: Repository, https://github.com/zeecaniago/rabbit
Project-URL: Issues, https://github.com/zeecaniago/rabbit/issues
Project-URL: Packages, https://github.com/zeecaniago/rabbit/packages
Keywords: ai,cli,chat,openai,anthropic,ollama
Classifier: Development Status :: 4 - Beta
Classifier: Intended Audience :: Developers
Classifier: License :: OSI Approved :: MIT License
Classifier: Operating System :: OS Independent
Classifier: Programming Language :: Python :: 3
Classifier: Programming Language :: Python :: 3.7
Classifier: Programming Language :: Python :: 3.8
Classifier: Programming Language :: Python :: 3.9
Classifier: Programming Language :: Python :: 3.10
Classifier: Programming Language :: Python :: 3.11
Classifier: Programming Language :: Python :: 3.12
Classifier: Topic :: Software Development :: Libraries :: Python Modules
Classifier: Topic :: Communications :: Chat
Classifier: Topic :: Scientific/Engineering :: Artificial Intelligence
Requires-Python: >=3.7
License-File: LICENSE
Requires-Dist: requests>=2.25.0
Requires-Dist: python-dotenv>=0.19.0
Provides-Extra: dev
Requires-Dist: pytest>=6.0.0; extra == "dev"
Requires-Dist: pytest-cov>=2.10.0; extra == "dev"
Requires-Dist: black>=22.0.0; extra == "dev"
Requires-Dist: flake8>=4.0.0; extra == "dev"
Dynamic: license-file
